<?xml version="1.0" encoding="utf-8" ?>
<ultimatezones>
  <!-- Zone Adding -->
  <locale  key="add_child_positionerror"	                   text="§redDi Position befendet sech nöd ennerhalb vo de öbergordnete Groppe oder Zone!" />
  <locale  key="add_collide_child"	                         text="§redDi Zone kollidiert met de Zone §gold{0}§red vo de Groppe §gold{1}§red!" />
  <locale  key="add_collide_parent"	                         text="§redDi Zone kollidiert met ere Zone vo de Groppe §gold{0}§red!" />
  <locale  key="add_success_child"	                         text="§darkgreenDi Zone esch erfolgrich de Groppe §gold{0}§darkgreen hinzugefügt worde!" />
  <locale  key="add_success_parent"	                         text="§darkgreenDi Zone esch erfolgrich de Groppe §gold{0}§darkgreen hinzugefügt worde!" />
  <locale  key="add_error_groups"	                           text="§redDu dörfsch maximal §gold{0}§red Groppen besetze!" />
  <locale  key="add_error_parents"	                         text="§redDu dörfsch maximal §gold{0}§red normali Zonen besetze!" />
  <locale  key="add_error_child"	                           text="§redDu dörfsch maximal §gold{0}§red KindZonen besetze!" />
  <locale  key="add_error_area"	                             text="§redDu dörfsch d'maximal Flächi vo alle Zonen esch uf §gold{0}§red begränzt!" />
  <locale  key="add_error_world"	                           text="§redIn dere Wält send kei Zone erlaubt!" />
  <locale  key="add_error_maxlength"	                       text="§redDi Site dörfed maximal §gold{0}§red lang si!" />
  <locale  key="add_error_minlength"	                       text="§redDi Site mössed mindestens §gold{0}§red lang si!" />
  <locale  key="add_error_aspectratio"	                     text="§redDi Site dörfed untereinader maximal §gold{0}§red so lang si!" />

  <!-- Shared Messages -->
  <locale  key="shared_unknowngroup"	                       text="§redDi Zonegroppe §gold{0}§red existiert nöd!" />
  <locale  key="shared_existinggroup"	                       text="§redDi Zonegroppe §gold{0}§red existiert scho ond ghört §gold{1}§red!" />
  <locale  key="shared_unknowngroup"	                       text="§redDi Zonegroppe §gold{0}§red existiert nöd!" />
  <locale  key="shared_nogrouprights"	                       text="§redDu dörfsch d'Zonegroppe §gold{0}§red nöd bearbeiten!" />
  <locale  key="shared_unknownright"	                       text="§redDas Rächt §gold{0}§red esch nöd gfonde worde!" />
  <locale  key="shared_unknownzone"	                         text="§redDi Zone §gold{0}§red esch ned gfonde worde!" />
  <locale  key="shared_nochildzone"	                         text="§redDi Zone §gold{0}§red esch kei KindZone!" />
  <locale  key="shared_nozonerights"	                       text="§redDu dörsch d'Zone §gold{0}§red nöd bearbeiten!" />
  <locale  key="shared_nobuildingrights"	                   text="§redDu hesch ned gnügend Rächt i de Groppe §gold{1}§red (Zone: §gold{0}§red) für die Aktion!" />
  <locale  key="shared_unknownpreset"	                       text="§redDas Preset §gold{0}§red esch ned gfonde worde!" />
  
  <!-- Commands -->
  <locale  key="groupcommand_add_maxgroups"	                 text="§redDu hesch das Limit vo §gold{0}§red Zonegruppe erreicht!" />
  <locale  key="groupcommand_add_success"	                   text="§darkgreenDi Zonegrupp §gold{0}§darkgreen esch §gold{1}§darkgreen angleid worde!" />
  <locale  key="groupcommand_del_success"	                   text="§darkgreenDi Zonegrupp §gold{0}§darkgreen esch §redgelöscht§darkgreen worde!" />
  <locale  key="groupcommand_right_toggle"	                 text="§darkgreenDas Rächt §gold{0}§darkgreen för die Groppe §gold{1}§darkgreen wurde {If,{2}}§greenhinzugefügt{Else}§redentfernt{EndIf}" /> 
  <locale  key="groupcommand_group_list"	                   text="§darkgreenEs send §gold{0}§darkgreen Standarträcht för die Groppe §gold{1}§darkgreenvergeben: §gold{2}worde" />
  <locale  key="groupcommand_group_list_empty"	             text="§redEs send besher kei Standarträcht vergeh worde!" />
  <locale  key="groupcommand_list"	                         text="§darkgreenEs ged §gold{0}§darkgreen Rechte wo vergeh wärde chönd: §gold{1}" />
  
  <locale  key="rightscommand_group_list"	                   text="§darkgreenFör die Groppe §gold{0}§darkgreen send Rächt verteilt worde a: §gold{1}" />  
  <locale  key="rightscommand_group_list_empty"	             text="§redEs send besher kei Rächt vergeh worde!" />
  <locale  key="rightscommand_group_list_player"	           text="§darkgreenEs es send folgendi Rächt a §gold{0}§darkgreen vergäh: §gold{1}" />
  <locale  key="rightscommand_group_list_player_empty"	     text="§redEs send besher kei Rächt a §gold{0}§red vergäh!" />
  <locale  key="rightscommand_group_clear"	                 text="§redEs send alli vergebne Rächt i dere Groppe §gold{0}§red entfernt worde!" />
  <locale  key="rightscommand_group_clear_player"	           text="§redEs send alli Rächt §gold{0}§red i dere Groppe §gold{1}§red entfernt worde!" />
  <locale  key="rightscommand_group_set_right"	             text="§gold{0}§darkgreen esch för die Groppe §gold{1}§darkgreen  s'Rächt §gold{2} {If,{3}}§greengegeben{Else}§redgenommen{EndIf}§darkgreen!" />
  <locale  key="rightscommand_group_set_place"	             text="§darkgreenFör §gold{0}§darkgreen esch i de Groppe §gold{1} {2} §darkgreender§gold Place Liste {If,{3}}§greenhinzugefügt{Else}§redentfernt{EndIf}§darkgreen!worde" />
  <locale  key="rightscommand_group_set_break"	             text="§darkgreenFör §gold{0}§darkgreen esch i de Groppe §gold{1} {2} §darkgreender§gold Break Liste {If,{3}}§greenhinzugefügt{Else}§redentfernt{EndIf}§darkgreen!worde" />  
  <locale  key="rightscommand_group_set_preset"	             text="§gold{0}§darkgreen esch för die Groppe §gold{1}§darkgreen  s'Preset §gold{2}§darkgreen zugwese worde!" />
  <locale  key="rightscommand_zone_list"	                   text="§darkgreenFör di Zone §gold{0}§darkgreen sind Rächt verteilt a: §gold{1}" />  
  <locale  key="rightscommand_zone_list_empty"	             text="§redEs send besher kei Rächt vergeh worde!" />
  <locale  key="rightscommand_zone_list_player"	             text="§darkgreenEs send folgendi Rächt §gold{0}§darkgreen vergäh: §gold{1}" />
  <locale  key="rightscommand_zone_list_player_empty"	       text="§redEs send besher kei Rächt §gold{0}§red vergäh!" />
  <locale  key="rightscommand_zone_clear"	                   text="§redEs sende alli vergebene Rächt för §gold{0}§red entfernt worde!" />
  <locale  key="rightscommand_zone_clear_player"	           text="§redEs send alli Rächt §gold{0}§red i dere Zone §gold{1}§red entfernt worden!" />
  <locale  key="rightscommand_zone_set_right"	               text="§gold{0}§darkgreen esch för die Zone §gold{1}§darkgreen s'Rächt §gold{2} {If,{3}}§greengegeben{Else}§redgenommen{EndIf}§darkgreenworden!" />
  <locale  key="rightscommand_zone_set_place"	               text="§darkgreenFör §gold{0}§darkgreen esch i de Zone  §gold{1} {2} §darkgreender§gold Place Liste {If,{3}}§greenhinzugefügt{Else}§redentfernt{EndIf}§darkgreen worde!" />
  <locale  key="rightscommand_zone_set_break"	               text="§darkgreenFör §gold{0}§darkgreen esch i de Zone §gold{1} {2} §darkgreender§gold Break Liste {If,{3}}§greenhinzugefügt{Else}§redentfernt{EndIf}§darkgreen worde!" />  
  <locale  key="rightscommand_zone_set_preset"	             text="§gold{0}§darkgreen esch för d'Zone §gold{1}§darkgreen s'Preset §gold{2}§darkgreen zugewiesen worden!" />
  <locale  key="rightscommand_list"	                         text="§darkgreenEs get momentan §gold{0}§darkgreen Rächte: §gold{1}" />  
  <locale  key="rightscommand_list_presets"	                 text="§darkgreenEs get momentan §gold{0}§darkgreen Presets: §gold{1}" />

  <locale  key="zonecommand_add_parent"	                     text="§greenDi Erstellig het agfange!" />
  <locale  key="zonecommand_add_child"	                     text="§greenDi Erstellig het agfange!" />
  <locale  key="zonecommand_add_abort"	                     text="§redDi Zoneerstellig wurde abgebrochen!" />
  <locale  key="zonecommand_del_success"	                   text="§redDi Zone §gold{0}§red esch glöscht worde!" />
  
</ultimatezones>
